dodoco/__init__.py
dodoco/psdr_cuda.cp38-win_amd64.pyd
dodoco-0.0.1.dist-info/LICENSE
dodoco-0.0.1.dist-info/METADATA
dodoco-0.0.1.dist-info/WHEEL
dodoco-0.0.1.dist-info/top_level.txt
dodoco-0.0.1.dist-info/RECORD
